qsalto/__init__.py
qsalto/matrices.py
qsalto/mp_not_available.py
qsalto/naive_matrices.py
qsalto/single_entry.py
qsalto/single_entry_precise.py
qsalto/single_shot.py
qsalto-0.2.1.dist-info/LICENSE
qsalto-0.2.1.dist-info/METADATA
qsalto-0.2.1.dist-info/WHEEL
qsalto-0.2.1.dist-info/top_level.txt
qsalto-0.2.1.dist-info/RECORD
