Metadata-Version: 2.2
Name: qsalto
Version: 0.2.1
Summary: Transformations between quantum weight enumerators
Author: Mc-Zen
Project-URL: Homepage, https://github.com/Mc-Zen/qsalto
Project-URL: Bug Tracker, https://github.com/Mc-Zen/qsalto/issues
Keywords: quantum information,quantum weight enumerators,Shor-Laflamme,Rains unitary,Rains shadow
Classifier: Programming Language :: Python :: 3
Classifier: License :: OSI Approved :: MIT License
Classifier: Operating System :: OS Independent
Classifier: Topic :: Scientific/Engineering :: Physics
Classifier: Topic :: Scientific/Engineering :: Mathematics
Classifier: Intended Audience :: Science/Research
Requires-Python: >=3.8
License-File: LICENSE
Requires-Dist: numpy>=1.22
Provides-Extra: precision
Requires-Dist: mpmath>=1.0; extra == "precision"
